sphinx_notebook/__init__.py
sphinx_notebook/cli.py
sphinx_notebook/data.py
sphinx_notebook/filters.py
sphinx_notebook/notebook.py
sphinx_notebook/templates/index.rst.jinja
sphinx_notebook/templates/note.rst.jinja
sphinx_notebook/util.py
sphinx_notebook-0.10.1.dist-info/LICENSE
sphinx_notebook-0.10.1.dist-info/METADATA
sphinx_notebook-0.10.1.dist-info/WHEEL
sphinx_notebook-0.10.1.dist-info/entry_points.txt
sphinx_notebook-0.10.1.dist-info/RECORD
